ptwt-1.0.1.dist-info/METADATA
ptwt-1.0.1.dist-info/WHEEL
ptwt-1.0.1.dist-info/entry_points.txt
ptwt-1.0.1.dist-info/licenses/LICENSE
ptwt/__init__.py
ptwt/_util.py
ptwt/constants.py
ptwt/continuous_transform.py
ptwt/conv_transform.py
ptwt/conv_transform_2.py
ptwt/conv_transform_3.py
ptwt/matmul_transform.py
ptwt/matmul_transform_2.py
ptwt/matmul_transform_3.py
ptwt/packets.py
ptwt/py.typed
ptwt/separable_conv_transform.py
ptwt/sparse_math.py
ptwt/stationary_transform.py
ptwt/version.py
ptwt/wavelets_learnable.py
ptwt-1.0.1.dist-info/RECORD
