Metadata-Version: 2.1
Name: ptwt
Version: 1.0.1
Summary: Differentiable and gpu enabled fast wavelet transforms in PyTorch
Keywords: Wavelets,Wavelet Transform,Fast Wavelet Transform,Boundary Wavelets,PyTorch
Author-Email: Moritz Wolter and Felix Blanke <moritz@wolter.tech>
Maintainer-Email: Moritz Wolter and Felix Blanke <moritz@wolter.tech>
License: EUPL-1.2
Classifier: Development Status :: 4 - Beta
Classifier: Environment :: Console
Classifier: Intended Audience :: Science/Research
Classifier: License :: OSI Approved :: European Union Public Licence 1.2 (EUPL 1.2)
Classifier: Operating System :: OS Independent
Classifier: Programming Language :: Python
Classifier: Programming Language :: Python :: 3 :: Only
Classifier: Programming Language :: Python :: 3.12
Classifier: Programming Language :: Python :: 3.11
Classifier: Topic :: Scientific/Engineering :: Artificial Intelligence
Project-URL: Homepage, https://github.com/v0lta/PyTorch-Wavelet-Toolbox
Project-URL: Downloads, https://github.com/v0lta/PyTorch-Wavelet-Toolbox/releases
Project-URL: Bug Tracker, https://github.com/v0lta/PyTorch-Wavelet-Toolbox/issues
Project-URL: Source Code, https://github.com/v0lta/PyTorch-Wavelet-Toolbox
Requires-Python: >=3.11
Requires-Dist: PyWavelets
Requires-Dist: numpy
Requires-Dist: torch
Provides-Extra: tests
Requires-Dist: pooch; extra == "tests"
Requires-Dist: pytest; extra == "tests"
Requires-Dist: scipy>=1.10; extra == "tests"
Provides-Extra: typing
Requires-Dist: mypy>=1.11; extra == "typing"
Requires-Dist: pytest; extra == "typing"
Provides-Extra: examples
Requires-Dist: matplotlib; extra == "examples"
